friday.py
app/__init__.py
app/commands/__init__.py
app/commands/project/__init__.py
app/commands/project/info.py
app/common/__init__.py
app/common/aws.py
app/common/composer.py
app/common/config.py
omni_friday-0.0.8.dist-info/LICENSE
omni_friday-0.0.8.dist-info/METADATA
omni_friday-0.0.8.dist-info/WHEEL
omni_friday-0.0.8.dist-info/entry_points.txt
omni_friday-0.0.8.dist-info/top_level.txt
omni_friday-0.0.8.dist-info/RECORD
