Metadata-Version: 2.2
Name: omni-friday
Version: 0.0.8
Summary: FRIDAY is a console tool developed in Python that allows you to obtain and analyze key information from projects based on Adobe Commerce.
Home-page: https://github.com/omni-pro/friday
Author: Facundo Capua
Author-email: capua.facundo@omni.pro
License: MIT License
Classifier: Programming Language :: Python :: 3.8
Classifier: Operating System :: OS Independent
Requires-Python: >=3.7
License-File: LICENSE
Requires-Dist: click>=8.1.7
Requires-Dist: click_help_colors==0.9.4
Requires-Dist: PyYAML==6.0.2
Requires-Dist: boto3==1.35.83
Requires-Dist: python-dotenv==1.0.1
Dynamic: author
Dynamic: author-email
Dynamic: classifier
Dynamic: description
Dynamic: description-content-type
Dynamic: home-page
Dynamic: license
Dynamic: requires-dist
Dynamic: requires-python
Dynamic: summary
